ucla_geotech_tools/__init__.py
ucla_geotech_tools/auto_fchp.py
ucla_geotech_tools/eas.py
ucla_geotech_tools/ipyconsol.c
ucla_geotech_tools/ipyconsol.cp311-win_amd64.pyd
ucla_geotech_tools/ipyconsol.cpython-39-x86_64-linux-gnu.so
ucla_geotech_tools/ipyconsol.pyx
ucla_geotech_tools/random_field.c
ucla_geotech_tools/random_field.cp311-win_amd64.pyd
ucla_geotech_tools/random_field.cpython-39-x86_64-linux-gnu.so
ucla_geotech_tools/random_field.pyx
ucla_geotech_tools/response_spectrum.py
ucla_geotech_tools-3.0.1.dist-info/METADATA
ucla_geotech_tools-3.0.1.dist-info/WHEEL
ucla_geotech_tools-3.0.1.dist-info/licenses/LICENSE.txt
ucla_geotech_tools-3.0.1.dist-info/RECORD
