Metadata-Version: 2.4
Name: ucla_geotech_tools
Version: 3.0.1
Summary: A collection of software tools developed by the UCLA geotechnical group
License: LICENSE.txt
License-File: LICENSE.txt
Author: Scott J. Brandenberg
Requires-Python: >=3.8
Classifier: License :: Other/Proprietary License
Classifier: Programming Language :: Python :: 3
Classifier: Programming Language :: Python :: 3.8
Classifier: Programming Language :: Python :: 3.9
Classifier: Programming Language :: Python :: 3.10
Classifier: Programming Language :: Python :: 3.11
Classifier: Programming Language :: Python :: 3.12
Classifier: Programming Language :: Python :: 3.13
Classifier: Programming Language :: Python :: 3.14
Requires-Dist: numpy (>=1.22)
Requires-Dist: scipy (>=1.8)
